setup.py
alex_solver/__init__.py
alex_solver/solver.py
alex_solver.egg-info/PKG-INFO
alex_solver.egg-info/SOURCES.txt
alex_solver.egg-info/dependency_links.txt
alex_solver.egg-info/not-zip-safe
alex_solver.egg-info/top_level.txt