Metadata-Version: 1.0
Name: alex-solver
Version: 1.1
Summary: A Python package containing my preferred solutions to popular leetcode problems.
Home-page: UNKNOWN
Author: UNKNOWN
Author-email: UNKNOWN
License: UNKNOWN
Platform: UNKNOWN
